.DS_Store
homer/__init__.py
homer/analyzer.py
homer/cmdline_printer.py
homer/constants.py
homer/homer_cmd.py
homer/throwaway.py
homer/utils.py
homer_text-0.4.1.dist-info/LICENSE
homer_text-0.4.1.dist-info/METADATA
homer_text-0.4.1.dist-info/WHEEL
homer_text-0.4.1.dist-info/top_level.txt
homer_text-0.4.1.dist-info/RECORD
