Metadata-Version: 2.1
Name: homer-text
Version: 0.4.1
Summary: Homer, a text analyser in Python, can help make your text more clear, simple and useful for your readers.
Home-page: https://github.com/wyounas/homer
Author: Waqas Younas
Author-email: waqas.younas@gmail.com
License: MIT
Project-URL: Documentation, https://github.com/wyounas/homer
Project-URL: Source Code, https://github.com/wyounas/homer
Project-URL: Bug Tracker, https://github.com/wyounas/homer/issues
Keywords: text analyzer
Platform: UNKNOWN
Classifier: Development Status :: 3 - Alpha
Classifier: Intended Audience :: Developers
Classifier: Topic :: Text Processing :: Linguistic
Classifier: License :: OSI Approved :: MIT License
Classifier: Programming Language :: Python :: 3.4
Classifier: Programming Language :: Python :: 3.5
Classifier: Programming Language :: Python :: 3.6
Classifier: Programming Language :: Python :: 3.7
Requires-Dist: Click (==7.0)
Requires-Dist: colorclass (==2.2.0)
Requires-Dist: nltk (==3.4.1)
Requires-Dist: Pyphen (==0.9.5)
Requires-Dist: repoze.lru (==0.7)
Requires-Dist: six (==1.12.0)
Requires-Dist: terminaltables (==3.1.0)
Requires-Dist: textstat (==0.5.6)
